{
  "run_id": "run_20260417_012033_c0b2cedd",
  "date": "2026-04-17",
  "timestamp": "2026-04-17T01:22:40.888509",
  "global_filter": "abs(minv4gam - 497.6107675312575) < 76",
  "columns": {
    "combined_Pi0": "sqrt(pow(pi01Fit[5] - PhysicsConstants::mPi0, 2) + pow(pi02Fit[5] - PhysicsConstants::mPi0, 2))",
    "totalE": "pi01Fit[3] + pi02Fit[3]",
    "deltaT_MC": "KaonChTimeCMMC - KaonNeTimeCMMC",
    "deltaT": "KaonChTimeCMSignalFit - KaonNeTimeCMSignalFit"
  },
  "histograms": {
    "chi2": {
      "per_hist_filter": "",
      "combined_filter": "(abs(minv4gam - 497.6107675312575) < 76)",
      "variable": "Chi2SignalKinFit",
      "model": {
        "title": "Chi2 of the signal kinfit; #chi^{2} [-]; Entries",
        "nbins": 100,
        "xmin": 0,
        "xmax": 100,
        "dim": 1
      },
      "channels": {
        "Data": {
          "entries": 182998.0,
          "mean": 12.562537794628929,
          "rms": 6.767779060053135
        },
        "Signal": {
          "entries": 137556.0,
          "mean": 11.096825012286143,
          "rms": 5.963571761993341
        },
        "Regeneration": {
          "entries": 23925.0,
          "mean": 14.292017788188984,
          "rms": 6.9379094893335
        },
        "Omega": {
          "entries": 3057.0,
          "mean": 16.730564879785007,
          "rms": 6.90958176386451
        },
        "3pi0": {
          "entries": 16484.0,
          "mean": 17.221660730305185,
          "rms": 6.918671793645527
        },
        "Semileptonic": {
          "entries": 8571.0,
          "mean": 17.937610127889897,
          "rms": 6.864634633565553
        },
        "Other": {
          "entries": 4113.0,
          "mean": 13.406424229592451,
          "rms": 6.927738301627052
        },
        "pi+pi-pi+pi-": {
          "entries": 0.0,
          "mean": 0.0,
          "rms": 0.0
        },
        "MC sum": {
          "entries": 193706.0,
          "mean": 12.453318217044208,
          "rms": 6.665536798732856
        }
      },
      "purity": 0.7101277193272278,
      "efficiency": 0.9205010840761262,
      "signal_before": 149436,
      "signal_after": 137556.0,
      "background_after": 56150.0
    },
    "combined_Pi0": {
      "per_hist_filter": "",
      "combined_filter": "(abs(minv4gam - 497.6107675312575) < 76)",
      "variable": "combined_Pi0",
      "model": {
        "title": "Combined #pi^{0} mass; m [MeV]; Entries",
        "nbins": 100,
        "xmin": 0,
        "xmax": 10,
        "dim": 1
      },
      "channels": {
        "Data": {
          "entries": 182998.0,
          "mean": 4.801466200624398,
          "rms": 2.5190956445101347
        },
        "Signal": {
          "entries": 137556.0,
          "mean": 4.376488664683092,
          "rms": 2.434043078173658
        },
        "Regeneration": {
          "entries": 23925.0,
          "mean": 5.850457338108019,
          "rms": 2.443008193127842
        },
        "Omega": {
          "entries": 3057.0,
          "mean": 4.48132124033465,
          "rms": 2.4193593638269517
        },
        "3pi0": {
          "entries": 16484.0,
          "mean": 6.371357289225076,
          "rms": 2.31427090516202
        },
        "Semileptonic": {
          "entries": 8571.0,
          "mean": 5.787687200728724,
          "rms": 2.445355971301618
        },
        "Other": {
          "entries": 4113.0,
          "mean": 4.821390494511997,
          "rms": 2.5476259276785105
        },
        "pi+pi-pi+pi-": {
          "entries": 0.0,
          "mean": 0.0,
          "rms": 0.0
        },
        "MC sum": {
          "entries": 193706.0,
          "mean": 4.755885897816698,
          "rms": 2.525072141434186
        }
      },
      "purity": 0.7101277193272278,
      "efficiency": 0.9205010840761262,
      "signal_before": 149436,
      "signal_after": 137556.0,
      "background_after": 56150.0
    },
    "totalE_Pi0": {
      "per_hist_filter": "",
      "combined_filter": "(abs(minv4gam - 497.6107675312575) < 76)",
      "variable": "totalE",
      "model": {
        "title": "Total energy of #pi^{0} pair; E [MeV]; Entries",
        "nbins": 100,
        "xmin": 400,
        "xmax": 600,
        "dim": 1
      },
      "channels": {
        "Data": {
          "entries": 182998.0,
          "mean": 509.7455166349136,
          "rms": 1.0794126552115475
        },
        "Signal": {
          "entries": 137556.0,
          "mean": 509.75652439662827,
          "rms": 1.0769997460311378
        },
        "Regeneration": {
          "entries": 23925.0,
          "mean": 509.73552738025273,
          "rms": 1.019139743762423
        },
        "Omega": {
          "entries": 3057.0,
          "mean": 509.7638392721323,
          "rms": 1.064309261436664
        },
        "3pi0": {
          "entries": 16484.0,
          "mean": 509.79490638386994,
          "rms": 1.0842682261534788
        },
        "Semileptonic": {
          "entries": 8571.0,
          "mean": 509.7773132411515,
          "rms": 1.1284417889751661
        },
        "Other": {
          "entries": 4113.0,
          "mean": 509.7857041030661,
          "rms": 1.0880272316199693
        },
        "pi+pi-pi+pi-": {
          "entries": 0.0,
          "mean": 0.0,
          "rms": 0.0
        },
        "MC sum": {
          "entries": 193706.0,
          "mean": 509.7588521198496,
          "rms": 1.0731243778093627
        }
      },
      "purity": 0.7101277193272278,
      "efficiency": 0.9205010840761262,
      "signal_before": 149436,
      "signal_after": 137556.0,
      "background_after": 56150.0
    },
    "deltaT_MC": {
      "per_hist_filter": "",
      "combined_filter": "(abs(minv4gam - 497.6107675312575) < 76)",
      "variable": "deltaT_MC",
      "model": {
        "title": "Time difference MC Gen; t^{MC}_{ch} - t^{MC}_{ne} [#tau_{S}]; Entries",
        "nbins": 101,
        "xmin": -50,
        "xmax": 50,
        "dim": 1
      },
      "channels": {
        "Data": {
          "entries": 182998.0,
          "mean": 0.0,
          "rms": 0.0
        },
        "Signal": {
          "entries": 137556.0,
          "mean": -0.9064216858394089,
          "rms": 27.991152221036323
        },
        "Regeneration": {
          "entries": 23925.0,
          "mean": 0.0,
          "rms": 0.0
        },
        "Omega": {
          "entries": 3057.0,
          "mean": 0.0,
          "rms": 0.0
        },
        "3pi0": {
          "entries": 16484.0,
          "mean": -24.381643317722194,
          "rms": 14.660800290665163
        },
        "Semileptonic": {
          "entries": 8571.0,
          "mean": 24.14423943356864,
          "rms": 14.780618507218891
        },
        "Other": {
          "entries": 4113.0,
          "mean": 0.0,
          "rms": 0.0
        },
        "pi+pi-pi+pi-": {
          "entries": 0.0,
          "mean": 0.0,
          "rms": 0.0
        },
        "MC sum": {
          "entries": 193706.0,
          "mean": -0.7167285619267509,
          "rms": 21.540669532052608
        }
      },
      "purity": 0.7101277193272278,
      "efficiency": 0.9205010840761262,
      "signal_before": 149436,
      "signal_after": 137556.0,
      "background_after": 56150.0
    },
    "deltaT": {
      "per_hist_filter": "",
      "combined_filter": "(abs(minv4gam - 497.6107675312575) < 76)",
      "variable": "deltaT",
      "model": {
        "title": "Time difference; t^{fit}_{ch} - t^{fit}_{ne} [#tau_{S}]; Entries",
        "nbins": 101,
        "xmin": -50,
        "xmax": 50,
        "dim": 1
      },
      "channels": {
        "Data": {
          "entries": 182998.0,
          "mean": -1.6280259853258066,
          "rms": 27.989840594982205
        },
        "Signal": {
          "entries": 137556.0,
          "mean": -0.8814401956694525,
          "rms": 27.656053723121293
        },
        "Regeneration": {
          "entries": 23925.0,
          "mean": -7.323146088803349,
          "rms": 39.18555609962017
        },
        "Omega": {
          "entries": 3057.0,
          "mean": 1.1880643761039336,
          "rms": 2.7596090906738167
        },
        "3pi0": {
          "entries": 16484.0,
          "mean": -23.674521020126015,
          "rms": 15.095419402903385
        },
        "Semileptonic": {
          "entries": 8571.0,
          "mean": 23.553641907950027,
          "rms": 14.980946730706709
        },
        "Other": {
          "entries": 4113.0,
          "mean": 2.6012287132343084,
          "rms": 27.541438233758026
        },
        "pi+pi-pi+pi-": {
          "entries": 0.0,
          "mean": 0.0,
          "rms": 0.0
        },
        "MC sum": {
          "entries": 193706.0,
          "mean": -2.182298228561149,
          "rms": 29.69309877231602
        }
      },
      "purity": 0.7101277193272278,
      "efficiency": 0.9205010840761262,
      "signal_before": 149436,
      "signal_after": 137556.0,
      "background_after": 56150.0
    }
  }
}